README.md
setup.cfg
setup.py
beoplay/__init__.py
ha_beoplay.egg-info/PKG-INFO
ha_beoplay.egg-info/SOURCES.txt
ha_beoplay.egg-info/dependency_links.txt
ha_beoplay.egg-info/not-zip-safe
ha_beoplay.egg-info/top_level.txt