Metadata-Version: 1.1
Name: ha-beoplay
Version: 0.0.6
Summary: BeoPlay API for Home-Assistant
Home-page: https://github.com/martonborzak/ha-beoplay
Author: Marton Borzak
Author-email: hello@martonborzak.com
License: MIT License
Download-URL: https://github.com/martonborzak/ha-beoplay/tarball/0.0.6
Keywords: beoplay
Platform: any
Classifier: Intended Audience :: Developers
Classifier: License :: OSI Approved :: MIT License
Classifier: Operating System :: OS Independent
Classifier: Programming Language :: Python :: 3.4
